[
    {
        "train": 74.1042345276873,
        "test": 71.42857142857143,
        "tp_train": 81,
        "fp_train": 26,
        "tn_train": 374,
        "fn_train": 133,
        "tp_test": 15,
        "fp_test": 5,
        "tn_test": 95,
        "fn_test": 39,
        "timeTrain": 23.675925970077515,
        "timeEvaluateTrain": 0.06355476379394531,
        "timeEvaluateTest": 0.051783084869384766
    },
    {
        "train": 73.61563517915309,
        "test": 73.37662337662337,
        "tp_train": 73,
        "fp_train": 21,
        "tn_train": 379,
        "fn_train": 141,
        "tp_test": 18,
        "fp_test": 5,
        "tn_test": 95,
        "fn_test": 36,
        "timeTrain": 22.56607723236084,
        "timeEvaluateTrain": 0.06631135940551758,
        "timeEvaluateTest": 0.053327083587646484
    },
    {
        "train": 73.9413680781759,
        "test": 67.53246753246754,
        "tp_train": 87,
        "fp_train": 33,
        "tn_train": 367,
        "fn_train": 127,
        "tp_test": 14,
        "fp_test": 10,
        "tn_test": 90,
        "fn_test": 40,
        "timeTrain": 25.391427755355835,
        "timeEvaluateTrain": 0.08483171463012695,
        "timeEvaluateTest": 0.0736994743347168
    },
    {
        "train": 72.8013029315961,
        "test": 76.62337662337663,
        "tp_train": 85,
        "fp_train": 38,
        "tn_train": 362,
        "fn_train": 129,
        "tp_test": 25,
        "fp_test": 7,
        "tn_test": 93,
        "fn_test": 29,
        "timeTrain": 25.700668334960938,
        "timeEvaluateTrain": 0.07551217079162598,
        "timeEvaluateTest": 0.0563509464263916
    },
    {
        "train": 73.61563517915309,
        "test": 69.48051948051948,
        "tp_train": 77,
        "fp_train": 25,
        "tn_train": 375,
        "fn_train": 137,
        "tp_test": 12,
        "fp_test": 5,
        "tn_test": 95,
        "fn_test": 42,
        "timeTrain": 33.211689949035645,
        "timeEvaluateTrain": 0.11638140678405762,
        "timeEvaluateTest": 0.09157538414001465
    },
    {
        "train": 73.7785016286645,
        "test": 72.07792207792208,
        "tp_train": 79,
        "fp_train": 26,
        "tn_train": 374,
        "fn_train": 135,
        "tp_test": 16,
        "fp_test": 5,
        "tn_test": 95,
        "fn_test": 38,
        "timeTrain": 25.29242515563965,
        "timeEvaluateTrain": 0.09207773208618164,
        "timeEvaluateTest": 0.07736825942993164
    },
    {
        "train": 74.7557003257329,
        "test": 66.88311688311688,
        "tp_train": 92,
        "fp_train": 33,
        "tn_train": 367,
        "fn_train": 122,
        "tp_test": 16,
        "fp_test": 13,
        "tn_test": 87,
        "fn_test": 38,
        "timeTrain": 20.986003637313843,
        "timeEvaluateTrain": 0.06278228759765625,
        "timeEvaluateTest": 0.04970741271972656
    },
    {
        "train": 73.45276872964169,
        "test": 74.02597402597402,
        "tp_train": 80,
        "fp_train": 29,
        "tn_train": 371,
        "fn_train": 134,
        "tp_test": 22,
        "fp_test": 8,
        "tn_test": 92,
        "fn_test": 32,
        "timeTrain": 27.072047233581543,
        "timeEvaluateTrain": 0.06794190406799316,
        "timeEvaluateTest": 0.058548688888549805
    },
    {
        "train": 71.82410423452768,
        "test": 73.37662337662337,
        "tp_train": 71,
        "fp_train": 30,
        "tn_train": 370,
        "fn_train": 143,
        "tp_test": 22,
        "fp_test": 9,
        "tn_test": 91,
        "fn_test": 32,
        "timeTrain": 32.01996374130249,
        "timeEvaluateTrain": 0.09503579139709473,
        "timeEvaluateTest": 0.07841849327087402
    },
    {
        "train": 74.2671009771987,
        "test": 70.12987012987013,
        "tp_train": 78,
        "fp_train": 22,
        "tn_train": 378,
        "fn_train": 136,
        "tp_test": 16,
        "fp_test": 8,
        "tn_test": 92,
        "fn_test": 38,
        "timeTrain": 25.86813259124756,
        "timeEvaluateTrain": 0.08581876754760742,
        "timeEvaluateTest": 0.06906938552856445
    }
]