[
    {
        "train": 71.17263843648209,
        "test": 67.53246753246754,
        "tp_train": 88,
        "fp_train": 51,
        "tn_train": 349,
        "fn_train": 126,
        "tp_test": 16,
        "fp_test": 12,
        "tn_test": 88,
        "fn_test": 38,
        "timeTrain": 6.5690460205078125,
        "timeEvaluateTrain": 0.03189396858215332,
        "timeEvaluateTest": 0.01959395408630371
    },
    {
        "train": 70.35830618892508,
        "test": 72.72727272727273,
        "tp_train": 79,
        "fp_train": 47,
        "tn_train": 353,
        "fn_train": 135,
        "tp_test": 22,
        "fp_test": 10,
        "tn_test": 90,
        "fn_test": 32,
        "timeTrain": 8.332463026046753,
        "timeEvaluateTrain": 0.0377352237701416,
        "timeEvaluateTest": 0.0229952335357666
    },
    {
        "train": 71.00977198697069,
        "test": 70.12987012987013,
        "tp_train": 87,
        "fp_train": 51,
        "tn_train": 349,
        "fn_train": 127,
        "tp_test": 23,
        "fp_test": 15,
        "tn_test": 85,
        "fn_test": 31,
        "timeTrain": 7.455997705459595,
        "timeEvaluateTrain": 0.048563241958618164,
        "timeEvaluateTest": 0.027931928634643555
    },
    {
        "train": 74.42996742671009,
        "test": 69.48051948051948,
        "tp_train": 93,
        "fp_train": 36,
        "tn_train": 364,
        "fn_train": 121,
        "tp_test": 22,
        "fp_test": 15,
        "tn_test": 85,
        "fn_test": 32,
        "timeTrain": 8.374755620956421,
        "timeEvaluateTrain": 0.036885738372802734,
        "timeEvaluateTest": 0.019836902618408203
    },
    {
        "train": 71.00977198697069,
        "test": 71.42857142857143,
        "tp_train": 85,
        "fp_train": 49,
        "tn_train": 351,
        "fn_train": 129,
        "tp_test": 19,
        "fp_test": 9,
        "tn_test": 91,
        "fn_test": 35,
        "timeTrain": 8.489787817001343,
        "timeEvaluateTrain": 0.040317535400390625,
        "timeEvaluateTest": 0.02523350715637207
    },
    {
        "train": 70.68403908794788,
        "test": 72.72727272727273,
        "tp_train": 91,
        "fp_train": 57,
        "tn_train": 343,
        "fn_train": 123,
        "tp_test": 22,
        "fp_test": 10,
        "tn_test": 90,
        "fn_test": 32,
        "timeTrain": 7.630953073501587,
        "timeEvaluateTrain": 0.033041954040527344,
        "timeEvaluateTest": 0.02043914794921875
    },
    {
        "train": 72.31270358306189,
        "test": 72.72727272727273,
        "tp_train": 79,
        "fp_train": 35,
        "tn_train": 365,
        "fn_train": 135,
        "tp_test": 19,
        "fp_test": 7,
        "tn_test": 93,
        "fn_test": 35,
        "timeTrain": 8.320869207382202,
        "timeEvaluateTrain": 0.032090187072753906,
        "timeEvaluateTest": 0.02019977569580078
    },
    {
        "train": 72.9641693811075,
        "test": 67.53246753246754,
        "tp_train": 96,
        "fp_train": 48,
        "tn_train": 352,
        "fn_train": 118,
        "tp_test": 20,
        "fp_test": 16,
        "tn_test": 84,
        "fn_test": 34,
        "timeTrain": 9.538252830505371,
        "timeEvaluateTrain": 0.03626227378845215,
        "timeEvaluateTest": 0.022770404815673828
    },
    {
        "train": 71.17263843648209,
        "test": 68.18181818181819,
        "tp_train": 79,
        "fp_train": 42,
        "tn_train": 358,
        "fn_train": 135,
        "tp_test": 19,
        "fp_test": 14,
        "tn_test": 86,
        "fn_test": 35,
        "timeTrain": 9.688746452331543,
        "timeEvaluateTrain": 0.04910588264465332,
        "timeEvaluateTest": 0.023212671279907227
    },
    {
        "train": 72.14983713355049,
        "test": 69.48051948051948,
        "tp_train": 100,
        "fp_train": 57,
        "tn_train": 343,
        "fn_train": 114,
        "tp_test": 26,
        "fp_test": 19,
        "tn_test": 81,
        "fn_test": 28,
        "timeTrain": 7.974261045455933,
        "timeEvaluateTrain": 0.03346562385559082,
        "timeEvaluateTest": 0.02122950553894043
    }
]