[
    {
        "train": 75.8957654723127,
        "test": 75.97402597402598,
        "tp_train": 113,
        "fp_train": 47,
        "tn_train": 353,
        "fn_train": 101,
        "tp_test": 32,
        "fp_test": 15,
        "tn_test": 85,
        "fn_test": 22,
        "timeTrain": 31.803507804870605,
        "timeEvaluateTrain": 0.19173598289489746,
        "timeEvaluateTest": 0.10015678405761719
    },
    {
        "train": 75.57003257328991,
        "test": 70.12987012987013,
        "tp_train": 116,
        "fp_train": 52,
        "tn_train": 348,
        "fn_train": 98,
        "tp_test": 27,
        "fp_test": 19,
        "tn_test": 81,
        "fn_test": 27,
        "timeTrain": 36.11874961853027,
        "timeEvaluateTrain": 0.19823884963989258,
        "timeEvaluateTest": 0.10676312446594238
    },
    {
        "train": 75.7328990228013,
        "test": 72.07792207792208,
        "tp_train": 113,
        "fp_train": 48,
        "tn_train": 352,
        "fn_train": 101,
        "tp_test": 23,
        "fp_test": 12,
        "tn_test": 88,
        "fn_test": 31,
        "timeTrain": 39.20205903053284,
        "timeEvaluateTrain": 0.19791579246520996,
        "timeEvaluateTest": 0.1075737476348877
    },
    {
        "train": 75.8957654723127,
        "test": 72.07792207792208,
        "tp_train": 125,
        "fp_train": 59,
        "tn_train": 341,
        "fn_train": 89,
        "tp_test": 29,
        "fp_test": 18,
        "tn_test": 82,
        "fn_test": 25,
        "timeTrain": 41.131545305252075,
        "timeEvaluateTrain": 0.20366382598876953,
        "timeEvaluateTest": 0.10950350761413574
    },
    {
        "train": 77.0358306188925,
        "test": 68.83116883116882,
        "tp_train": 124,
        "fp_train": 51,
        "tn_train": 349,
        "fn_train": 90,
        "tp_test": 21,
        "fp_test": 15,
        "tn_test": 85,
        "fn_test": 33,
        "timeTrain": 37.26722049713135,
        "timeEvaluateTrain": 0.20176076889038086,
        "timeEvaluateTest": 0.10718512535095215
    },
    {
        "train": 77.1986970684039,
        "test": 66.88311688311688,
        "tp_train": 122,
        "fp_train": 48,
        "tn_train": 352,
        "fn_train": 92,
        "tp_test": 19,
        "fp_test": 16,
        "tn_test": 84,
        "fn_test": 35,
        "timeTrain": 40.66694402694702,
        "timeEvaluateTrain": 0.20355916023254395,
        "timeEvaluateTest": 0.11287856101989746
    },
    {
        "train": 74.9185667752443,
        "test": 76.62337662337663,
        "tp_train": 116,
        "fp_train": 56,
        "tn_train": 344,
        "fn_train": 98,
        "tp_test": 31,
        "fp_test": 13,
        "tn_test": 87,
        "fn_test": 23,
        "timeTrain": 40.10578417778015,
        "timeEvaluateTrain": 0.2324073314666748,
        "timeEvaluateTest": 0.12614846229553223
    },
    {
        "train": 75.4071661237785,
        "test": 77.27272727272727,
        "tp_train": 120,
        "fp_train": 57,
        "tn_train": 343,
        "fn_train": 94,
        "tp_test": 33,
        "fp_test": 14,
        "tn_test": 86,
        "fn_test": 21,
        "timeTrain": 41.33584547042847,
        "timeEvaluateTrain": 0.21140336990356445,
        "timeEvaluateTest": 0.17044496536254883
    },
    {
        "train": 75.7328990228013,
        "test": 79.87012987012987,
        "tp_train": 127,
        "fp_train": 62,
        "tn_train": 338,
        "fn_train": 87,
        "tp_test": 34,
        "fp_test": 11,
        "tn_test": 89,
        "fn_test": 20,
        "timeTrain": 36.767306327819824,
        "timeEvaluateTrain": 0.1989576816558838,
        "timeEvaluateTest": 0.10920166969299316
    },
    {
        "train": 76.54723127035831,
        "test": 75.32467532467533,
        "tp_train": 111,
        "fp_train": 41,
        "tn_train": 359,
        "fn_train": 103,
        "tp_test": 28,
        "fp_test": 12,
        "tn_test": 88,
        "fn_test": 26,
        "timeTrain": 39.25324988365173,
        "timeEvaluateTrain": 0.23902273178100586,
        "timeEvaluateTest": 0.13879823684692383
    }
]