[
    {
        "train": {
            "accuracy": 70.4225352112676,
            "loss": 1.0002743522326152,
            "confusion_matrix": [
                [
                    46,
                    0,
                    1
                ],
                [
                    2,
                    54,
                    1
                ],
                [
                    37,
                    1,
                    0
                ]
            ]
        },
        "test": {
            "accuracy": 69.44444444444444,
            "loss": 1.0048905611038208,
            "confusion_matrix": [
                [
                    11,
                    1,
                    0
                ],
                [
                    1,
                    13,
                    0
                ],
                [
                    9,
                    0,
                    1
                ]
            ]
        },
        "time": {
            "training_time": 7.27485990524292,
            "evaluation_train_time": 0.8501667976379395,
            "evaluation_test_time": 0.20131921768188477
        }
    },
    {
        "train": {
            "accuracy": 75.35211267605634,
            "loss": 0.9747538606325785,
            "confusion_matrix": [
                [
                    46,
                    1,
                    0
                ],
                [
                    3,
                    54,
                    0
                ],
                [
                    28,
                    3,
                    7
                ]
            ]
        },
        "test": {
            "accuracy": 72.22222222222223,
            "loss": 0.9809398651123047,
            "confusion_matrix": [
                [
                    12,
                    0,
                    0
                ],
                [
                    1,
                    13,
                    0
                ],
                [
                    8,
                    1,
                    1
                ]
            ]
        },
        "time": {
            "training_time": 7.7729387283325195,
            "evaluation_train_time": 0.8661582469940186,
            "evaluation_test_time": 0.20803475379943848
        }
    },
    {
        "train": {
            "accuracy": 68.30985915492958,
            "loss": 1.052411921819051,
            "confusion_matrix": [
                [
                    45,
                    1,
                    1
                ],
                [
                    10,
                    44,
                    3
                ],
                [
                    13,
                    17,
                    8
                ]
            ]
        },
        "test": {
            "accuracy": 61.111111111111114,
            "loss": 1.0557894110679626,
            "confusion_matrix": [
                [
                    12,
                    0,
                    0
                ],
                [
                    4,
                    10,
                    0
                ],
                [
                    4,
                    6,
                    0
                ]
            ]
        },
        "time": {
            "training_time": 6.263812303543091,
            "evaluation_train_time": 0.6958479881286621,
            "evaluation_test_time": 0.17729806900024414
        }
    },
    {
        "train": {
            "accuracy": 85.21126760563381,
            "loss": 1.0314716180165608,
            "confusion_matrix": [
                [
                    45,
                    0,
                    2
                ],
                [
                    3,
                    45,
                    9
                ],
                [
                    2,
                    5,
                    31
                ]
            ]
        },
        "test": {
            "accuracy": 97.22222222222223,
            "loss": 1.0179205238819122,
            "confusion_matrix": [
                [
                    11,
                    0,
                    1
                ],
                [
                    0,
                    14,
                    0
                ],
                [
                    0,
                    0,
                    10
                ]
            ]
        },
        "time": {
            "training_time": 10.173771381378174,
            "evaluation_train_time": 0.7172889709472656,
            "evaluation_test_time": 0.17943501472473145
        }
    },
    {
        "train": {
            "accuracy": 89.43661971830986,
            "loss": 0.9879223823547363,
            "confusion_matrix": [
                [
                    45,
                    1,
                    1
                ],
                [
                    4,
                    52,
                    1
                ],
                [
                    0,
                    8,
                    30
                ]
            ]
        },
        "test": {
            "accuracy": 86.11111111111111,
            "loss": 0.9912312775850296,
            "confusion_matrix": [
                [
                    11,
                    1,
                    0
                ],
                [
                    0,
                    14,
                    0
                ],
                [
                    1,
                    3,
                    6
                ]
            ]
        },
        "time": {
            "training_time": 6.070172071456909,
            "evaluation_train_time": 0.6606988906860352,
            "evaluation_test_time": 0.2081160545349121
        }
    },
    {
        "train": {
            "accuracy": 91.54929577464789,
            "loss": 0.971834929784139,
            "confusion_matrix": [
                [
                    43,
                    3,
                    1
                ],
                [
                    3,
                    51,
                    3
                ],
                [
                    0,
                    2,
                    36
                ]
            ]
        },
        "test": {
            "accuracy": 88.88888888888889,
            "loss": 0.9679060876369476,
            "confusion_matrix": [
                [
                    10,
                    2,
                    0
                ],
                [
                    0,
                    13,
                    1
                ],
                [
                    0,
                    1,
                    9
                ]
            ]
        },
        "time": {
            "training_time": 6.044812917709351,
            "evaluation_train_time": 0.686974287033081,
            "evaluation_test_time": 0.16213035583496094
        }
    },
    {
        "train": {
            "accuracy": 88.73239436619718,
            "loss": 0.9997590740521749,
            "confusion_matrix": [
                [
                    41,
                    0,
                    6
                ],
                [
                    2,
                    54,
                    1
                ],
                [
                    0,
                    7,
                    31
                ]
            ]
        },
        "test": {
            "accuracy": 94.44444444444444,
            "loss": 0.991343230009079,
            "confusion_matrix": [
                [
                    12,
                    0,
                    0
                ],
                [
                    0,
                    14,
                    0
                ],
                [
                    0,
                    2,
                    8
                ]
            ]
        },
        "time": {
            "training_time": 6.110310077667236,
            "evaluation_train_time": 0.6234371662139893,
            "evaluation_test_time": 0.16757583618164062
        }
    },
    {
        "train": {
            "accuracy": 89.43661971830986,
            "loss": 0.996574612458547,
            "confusion_matrix": [
                [
                    46,
                    0,
                    1
                ],
                [
                    7,
                    50,
                    0
                ],
                [
                    1,
                    6,
                    31
                ]
            ]
        },
        "test": {
            "accuracy": 80.55555555555556,
            "loss": 1.0237161964178085,
            "confusion_matrix": [
                [
                    10,
                    1,
                    1
                ],
                [
                    3,
                    11,
                    0
                ],
                [
                    1,
                    1,
                    8
                ]
            ]
        },
        "time": {
            "training_time": 6.067965745925903,
            "evaluation_train_time": 0.6849865913391113,
            "evaluation_test_time": 0.16575837135314941
        }
    },
    {
        "train": {
            "accuracy": 87.32394366197182,
            "loss": 1.0002589106559754,
            "confusion_matrix": [
                [
                    45,
                    2,
                    0
                ],
                [
                    2,
                    53,
                    2
                ],
                [
                    6,
                    6,
                    26
                ]
            ]
        },
        "test": {
            "accuracy": 88.88888888888889,
            "loss": 1.0022326409816742,
            "confusion_matrix": [
                [
                    11,
                    1,
                    0
                ],
                [
                    2,
                    12,
                    0
                ],
                [
                    0,
                    1,
                    9
                ]
            ]
        },
        "time": {
            "training_time": 5.9415318965911865,
            "evaluation_train_time": 0.6353409290313721,
            "evaluation_test_time": 0.16977286338806152
        }
    },
    {
        "train": {
            "accuracy": 69.71830985915493,
            "loss": 0.9961462100346883,
            "confusion_matrix": [
                [
                    45,
                    1,
                    1
                ],
                [
                    3,
                    54,
                    0
                ],
                [
                    4,
                    34,
                    0
                ]
            ]
        },
        "test": {
            "accuracy": 66.66666666666667,
            "loss": 1.0220000445842743,
            "confusion_matrix": [
                [
                    12,
                    0,
                    0
                ],
                [
                    1,
                    12,
                    1
                ],
                [
                    0,
                    10,
                    0
                ]
            ]
        },
        "time": {
            "training_time": 6.130581855773926,
            "evaluation_train_time": 0.6442101001739502,
            "evaluation_test_time": 0.18575072288513184
        }
    }
]