[
    {
        "train": 74.5928338762215,
        "test": 70.12987012987013,
        "tp_train": 358,
        "fp_train": 42,
        "tn_train": 114,
        "fn_train": 100,
        "tp_test": 90,
        "fp_test": 10,
        "tn_test": 36,
        "fn_test": 18,
        "timeTrain": 23.972089529037476,
        "timeEvaluateTrain": 0.05379891395568848,
        "timeEvaluateTest": 0.04634261131286621
    },
    {
        "train": 74.2671009771987,
        "test": 68.83116883116882,
        "tp_train": 375,
        "fp_train": 25,
        "tn_train": 133,
        "fn_train": 81,
        "tp_test": 90,
        "fp_test": 10,
        "tn_test": 38,
        "fn_test": 16,
        "timeTrain": 27.89210081100464,
        "timeEvaluateTrain": 0.05389237403869629,
        "timeEvaluateTest": 0.04626107215881348
    },
    {
        "train": 74.1042345276873,
        "test": 72.07792207792208,
        "tp_train": 358,
        "fp_train": 42,
        "tn_train": 117,
        "fn_train": 97,
        "tp_test": 88,
        "fp_test": 12,
        "tn_test": 31,
        "fn_test": 23,
        "timeTrain": 26.33255386352539,
        "timeEvaluateTrain": 0.05782032012939453,
        "timeEvaluateTest": 0.04928922653198242
    },
    {
        "train": 72.8013029315961,
        "test": 75.97402597402598,
        "tp_train": 360,
        "fp_train": 40,
        "tn_train": 127,
        "fn_train": 87,
        "tp_test": 93,
        "fp_test": 7,
        "tn_test": 30,
        "fn_test": 24,
        "timeTrain": 21.26230216026306,
        "timeEvaluateTrain": 0.05201077461242676,
        "timeEvaluateTest": 0.04499936103820801
    },
    {
        "train": 72.9641693811075,
        "test": 72.07792207792208,
        "tp_train": 376,
        "fp_train": 24,
        "tn_train": 142,
        "fn_train": 72,
        "tp_test": 94,
        "fp_test": 6,
        "tn_test": 37,
        "fn_test": 17,
        "timeTrain": 20.893524408340454,
        "timeEvaluateTrain": 0.0569608211517334,
        "timeEvaluateTest": 0.04690885543823242
    },
    {
        "train": 74.5928338762215,
        "test": 72.72727272727273,
        "tp_train": 366,
        "fp_train": 34,
        "tn_train": 122,
        "fn_train": 92,
        "tp_test": 89,
        "fp_test": 11,
        "tn_test": 31,
        "fn_test": 23,
        "timeTrain": 21.12342071533203,
        "timeEvaluateTrain": 0.05192899703979492,
        "timeEvaluateTest": 0.04535245895385742
    },
    {
        "train": 73.7785016286645,
        "test": 70.12987012987013,
        "tp_train": 369,
        "fp_train": 31,
        "tn_train": 130,
        "fn_train": 84,
        "tp_test": 89,
        "fp_test": 11,
        "tn_test": 35,
        "fn_test": 19,
        "timeTrain": 19.68445110321045,
        "timeEvaluateTrain": 0.05288243293762207,
        "timeEvaluateTest": 0.04643821716308594
    },
    {
        "train": 73.7785016286645,
        "test": 71.42857142857143,
        "tp_train": 370,
        "fp_train": 30,
        "tn_train": 131,
        "fn_train": 83,
        "tp_test": 92,
        "fp_test": 8,
        "tn_test": 36,
        "fn_test": 18,
        "timeTrain": 20.18516206741333,
        "timeEvaluateTrain": 0.0703890323638916,
        "timeEvaluateTest": 0.05567789077758789
    },
    {
        "train": 75.0814332247557,
        "test": 66.88311688311688,
        "tp_train": 368,
        "fp_train": 32,
        "tn_train": 121,
        "fn_train": 93,
        "tp_test": 85,
        "fp_test": 15,
        "tn_test": 36,
        "fn_test": 18,
        "timeTrain": 19.493774890899658,
        "timeEvaluateTrain": 0.054224491119384766,
        "timeEvaluateTest": 0.0445551872253418
    },
    {
        "train": 73.9413680781759,
        "test": 71.42857142857143,
        "tp_train": 365,
        "fp_train": 35,
        "tn_train": 125,
        "fn_train": 89,
        "tp_test": 88,
        "fp_test": 12,
        "tn_test": 32,
        "fn_test": 22,
        "timeTrain": 19.358886003494263,
        "timeEvaluateTrain": 0.05802488327026367,
        "timeEvaluateTest": 0.0448298454284668
    }
]