[
    {
        "train": 76.0586319218241,
        "test": 71.42857142857143,
        "tp_train": 344,
        "fp_train": 56,
        "tn_train": 91,
        "fn_train": 123,
        "tp_test": 89,
        "fp_test": 11,
        "tn_test": 33,
        "fn_test": 21,
        "timeTrain": 49.638920307159424,
        "timeEvaluateTrain": 0.286815881729126,
        "timeEvaluateTest": 0.20272064208984375
    },
    {
        "train": 78.82736156351791,
        "test": 66.23376623376623,
        "tp_train": 348,
        "fp_train": 52,
        "tn_train": 78,
        "fn_train": 136,
        "tp_test": 83,
        "fp_test": 17,
        "tn_test": 35,
        "fn_test": 19,
        "timeTrain": 43.73922777175903,
        "timeEvaluateTrain": 0.24383068084716797,
        "timeEvaluateTest": 0.13208222389221191
    },
    {
        "train": 78.0130293159609,
        "test": 66.23376623376623,
        "tp_train": 346,
        "fp_train": 54,
        "tn_train": 81,
        "fn_train": 133,
        "tp_test": 79,
        "fp_test": 21,
        "tn_test": 31,
        "fn_test": 23,
        "timeTrain": 42.624696254730225,
        "timeEvaluateTrain": 0.280778169631958,
        "timeEvaluateTest": 0.13971471786499023
    },
    {
        "train": 77.85016286644951,
        "test": 75.97402597402598,
        "tp_train": 355,
        "fp_train": 45,
        "tn_train": 91,
        "fn_train": 123,
        "tp_test": 87,
        "fp_test": 13,
        "tn_test": 24,
        "fn_test": 30,
        "timeTrain": 44.88964819908142,
        "timeEvaluateTrain": 0.23987197875976562,
        "timeEvaluateTest": 0.13396000862121582
    },
    {
        "train": 78.17589576547232,
        "test": 71.42857142857143,
        "tp_train": 349,
        "fp_train": 51,
        "tn_train": 83,
        "fn_train": 131,
        "tp_test": 81,
        "fp_test": 19,
        "tn_test": 25,
        "fn_test": 29,
        "timeTrain": 42.018784046173096,
        "timeEvaluateTrain": 0.27103447914123535,
        "timeEvaluateTest": 0.1295156478881836
    },
    {
        "train": 74.9185667752443,
        "test": 72.07792207792208,
        "tp_train": 338,
        "fp_train": 62,
        "tn_train": 92,
        "fn_train": 122,
        "tp_test": 84,
        "fp_test": 16,
        "tn_test": 27,
        "fn_test": 27,
        "timeTrain": 41.53552746772766,
        "timeEvaluateTrain": 0.28699254989624023,
        "timeEvaluateTest": 0.14257240295410156
    },
    {
        "train": 77.0358306188925,
        "test": 70.77922077922078,
        "tp_train": 347,
        "fp_train": 53,
        "tn_train": 88,
        "fn_train": 126,
        "tp_test": 82,
        "fp_test": 18,
        "tn_test": 27,
        "fn_test": 27,
        "timeTrain": 39.54116606712341,
        "timeEvaluateTrain": 0.23431706428527832,
        "timeEvaluateTest": 0.12299227714538574
    },
    {
        "train": 78.82736156351791,
        "test": 70.77922077922078,
        "tp_train": 359,
        "fp_train": 41,
        "tn_train": 89,
        "fn_train": 125,
        "tp_test": 82,
        "fp_test": 18,
        "tn_test": 27,
        "fn_test": 27,
        "timeTrain": 39.328052282333374,
        "timeEvaluateTrain": 0.24035310745239258,
        "timeEvaluateTest": 0.12849068641662598
    },
    {
        "train": 77.68729641693811,
        "test": 72.07792207792208,
        "tp_train": 352,
        "fp_train": 48,
        "tn_train": 89,
        "fn_train": 125,
        "tp_test": 81,
        "fp_test": 19,
        "tn_test": 24,
        "fn_test": 30,
        "timeTrain": 39.61228013038635,
        "timeEvaluateTrain": 0.24372649192810059,
        "timeEvaluateTest": 0.126021146774292
    },
    {
        "train": 77.1986970684039,
        "test": 72.72727272727273,
        "tp_train": 359,
        "fp_train": 41,
        "tn_train": 99,
        "fn_train": 115,
        "tp_test": 85,
        "fp_test": 15,
        "tn_test": 27,
        "fn_test": 27,
        "timeTrain": 39.16764235496521,
        "timeEvaluateTrain": 0.23708033561706543,
        "timeEvaluateTest": 0.12513136863708496
    }
]